win32_pipes/__init__.py
win32_pipes/_ext.pyd
win32_pipes/_ext.pyi
win32_pipes/py.typed
win32_pipes-0.2.1.dist-info/METADATA
win32_pipes-0.2.1.dist-info/WHEEL
win32_pipes-0.2.1.dist-info/entry_points.txt
win32_pipes-0.2.1.dist-info/licenses/LICENSE
win32_pipes-0.2.1.dist-info/RECORD
